core/__init__.py
core/dal/__init__.py
core/dal/data.py
core/dal/database_errors.py
core/dal/postgres_connection.py
core/dal/postgres_repository.py
core/di/__init__.py
core/di/data.py
core/di/injector.py
core/rest/__init__.py
core/rest/app_controller.py
core/rest/app_module.py
core/rest/data.py
core/rules_engine/__init__.py
core/rules_engine/data.py
core/rules_engine/exceptions.py
core/rules_engine/rule_manager.py
core/utils/__init__.py
core/utils/convert.py
core/utils/data.py
braincube_aws_core_alpha-0.0.31.dist-info/LICENSE
braincube_aws_core_alpha-0.0.31.dist-info/METADATA
braincube_aws_core_alpha-0.0.31.dist-info/WHEEL
braincube_aws_core_alpha-0.0.31.dist-info/top_level.txt
braincube_aws_core_alpha-0.0.31.dist-info/RECORD
